gstreamer_msvc_runtime-1.27.90.data/purelib/gstreamer_msvc_runtime/__init__.py
gstreamer_msvc_runtime-1.27.90.data/purelib/gstreamer_msvc_runtime/bin/concrt140.dll
gstreamer_msvc_runtime-1.27.90.data/purelib/gstreamer_msvc_runtime/bin/msvcp140.dll
gstreamer_msvc_runtime-1.27.90.data/purelib/gstreamer_msvc_runtime/bin/msvcp140_1.dll
gstreamer_msvc_runtime-1.27.90.data/purelib/gstreamer_msvc_runtime/bin/msvcp140_2.dll
gstreamer_msvc_runtime-1.27.90.data/purelib/gstreamer_msvc_runtime/bin/msvcp140_atomic_wait.dll
gstreamer_msvc_runtime-1.27.90.data/purelib/gstreamer_msvc_runtime/bin/msvcp140_codecvt_ids.dll
gstreamer_msvc_runtime-1.27.90.data/purelib/gstreamer_msvc_runtime/bin/vcamp140.dll
gstreamer_msvc_runtime-1.27.90.data/purelib/gstreamer_msvc_runtime/bin/vccorlib140.dll
gstreamer_msvc_runtime-1.27.90.data/purelib/gstreamer_msvc_runtime/bin/vcomp140.dll
gstreamer_msvc_runtime-1.27.90.data/purelib/gstreamer_msvc_runtime/bin/vcruntime140.dll
gstreamer_msvc_runtime-1.27.90.data/purelib/gstreamer_msvc_runtime/bin/vcruntime140_1.dll
gstreamer_msvc_runtime-1.27.90.data/purelib/gstreamer_msvc_runtime/bin/vcruntime140_threads.dll
gstreamer_msvc_runtime-1.27.90.dist-info/METADATA
gstreamer_msvc_runtime-1.27.90.dist-info/WHEEL
gstreamer_msvc_runtime-1.27.90.dist-info/top_level.txt
gstreamer_msvc_runtime-1.27.90.dist-info/RECORD
