Metadata-Version: 2.4
Name: gstreamer_msvc_runtime
Version: 1.27.90
Summary: GStreamer 1.0
Home-page: http://gstreamer.freedesktop.org
Author: GStreamer Project
License: LicenseRef-Proprietary
Classifier: Development Status :: 4 - Beta
Classifier: Intended Audience :: Developers
Classifier: Programming Language :: Python :: 3
Classifier: Topic :: Multimedia :: Graphics
Classifier: Topic :: Multimedia :: Sound/Audio
Classifier: Topic :: Multimedia :: Video
Classifier: Topic :: Software Development
Classifier: Topic :: Utilities
Classifier: Environment :: MacOS X
Classifier: Operating System :: MacOS :: MacOS X
Classifier: Environment :: Win32 (MS Windows)
Classifier: Operating System :: Microsoft :: Windows
Requires-Python: >= 3.9
Dynamic: author
Dynamic: classifier
Dynamic: home-page
Dynamic: license
Dynamic: requires-python
Dynamic: summary
